<?xml version="1.0" encoding="utf-8" ?><dwsync><file name=".DS_Store" server="s251035938.onlinehome.us" local="3535338099" remote="12125286572" /><file name="1.jpg" server="s251035938.onlinehome.us" local="3535338667" remote="12125286572" /><file name="2.jpg" server="s251035938.onlinehome.us" local="3535338715" remote="12125286572" /><file name="3.jpg" server="s251035938.onlinehome.us" local="3535338761" remote="12125286572" /><file name="4.jpg" server="s251035938.onlinehome.us" local="3535338902" remote="12125286572" /><file name="5.jpg" server="s251035938.onlinehome.us" local="3535338929" remote="12125286572" /><file name="6.jpg" server="s251035938.onlinehome.us" local="3535338981" remote="12125286572" /><file name="7.jpg" server="s251035938.onlinehome.us" local="3535339039" remote="12125286572" /><file name="1t.jpg" server="s251035938.onlinehome.us" local="3535341823" remote="16420254648" /></dwsync>